src/README.md
src/art.py
src/main.py
src/styles.css.txt
pyrain_weather-0.1.1.dist-info/METADATA
pyrain_weather-0.1.1.dist-info/WHEEL
pyrain_weather-0.1.1.dist-info/entry_points.txt
pyrain_weather-0.1.1.dist-info/licenses/LICENSE
pyrain_weather-0.1.1.dist-info/RECORD
