Metadata-Version: 2.4
Name: pyrain-weather
Version: 0.1.1
Summary: Weather tui app written in python
Project-URL: Homepage, https://github.com/dear-satan/pyrain-weather
Author-email: Dear_satan <jakubj1406@gmail.com>
License-Expression: MIT
License-File: LICENSE
Classifier: Operating System :: OS Independent
Classifier: Programming Language :: Python :: 3
Requires-Python: >=3.9
Requires-Dist: httpx
Requires-Dist: rich
Requires-Dist: textual
